minnie_config/__init__.py
minnie_config/adapters.py
minnie_config/cli.py
minnie_config/minnie65_config.py
minnie_config-0.1.0.dist-info/LICENSE
minnie_config-0.1.0.dist-info/METADATA
minnie_config-0.1.0.dist-info/WHEEL
minnie_config-0.1.0.dist-info/entry_points.txt
minnie_config-0.1.0.dist-info/top_level.txt
minnie_config-0.1.0.dist-info/RECORD
