Metadata-Version: 2.1
Name: minnie-config
Version: 0.1.0
Summary: Datajoint configurations for the microns_minnie65_* phase 3 schemas.
Home-page: UNKNOWN
Author: Christos Papadopoulos
Author-email: cpapadop@bcm.edu
License: UNKNOWN
Platform: UNKNOWN
Requires-Dist: datajoint (>=0.12.3)
Requires-Dist: numpy
Requires-Dist: h5py
